apextras/__init__.py
apextras/formatter/__init__.py
apextras/formatter/wide.py
apextras-0.9.1.dist-info/LICENSE
apextras-0.9.1.dist-info/METADATA
apextras-0.9.1.dist-info/WHEEL
apextras-0.9.1.dist-info/top_level.txt
apextras-0.9.1.dist-info/RECORD
