Metadata-Version: 2.1
Name: apextras
Version: 0.9.1
Summary: Some helpers for python's argparse
Home-page: https://github.com/pypyr-scheduler/python-argparse-extras
Author: David Zerrenner
Author-email: dazer017@gmail.com
License: UNKNOWN
Platform: UNKNOWN
Classifier: Programming Language :: Python :: 3
Classifier: License :: OSI Approved :: MIT License
Classifier: Operating System :: OS Independent
Requires-Python: >=3.6
